photopea/__init__.py
photopea/age_net.caffemodel
photopea/deploy.prototxt.txt
photopea/deploy_age.prototxt
photopea/deploy_gender.prototxt
photopea/gender_net.caffemodel
photopea/getface.py
photopea/res10_300x300_ssd_iter_140000_fp16.caffemodel
photopea-0.0.6.dist-info/LICENSE
photopea-0.0.6.dist-info/METADATA
photopea-0.0.6.dist-info/WHEEL
photopea-0.0.6.dist-info/top_level.txt
photopea-0.0.6.dist-info/RECORD
