Metadata-Version: 2.1
Name: photopea
Version: 0.0.6
Summary: Photo and Video convertor
Home-page: https://github.com/icodernet/
Author: iCoderNet
Author-email: iCoderNet@gmail.com
Classifier: Programming Language :: Python :: 3
Classifier: License :: OSI Approved :: MIT License
Classifier: Operating System :: OS Independent
Requires-Python: >=3.7
License-File: LICENSE
